Metadata-Version: 2.1
Name: sskp
Version: 2.0
Summary: package for file storage
Author: Sahil
Author-email: sahilapte14@gmail.com
Keywords: ngitkmit,store files,database,store,file,ngit,mongo,kmit
Classifier: Development Status :: 1 - Planning
Classifier: Intended Audience :: Developers
Classifier: Programming Language :: Python :: 3
Classifier: Operating System :: Unix
Classifier: Operating System :: MacOS :: MacOS X
Classifier: Operating System :: Microsoft :: Windows
License-File: LICENCE
